naas/__init__.py
naas/api.py
naas/dependency.py
naas/manager.py
naas/refresh.py
naas/secret.py
naas/static.py
naas/types.py
naas/runner/__init__.py
naas/runner/__main__.py
naas/runner/jobs.py
naas/runner/logger.py
naas/runner/notebooks.py
naas/runner/notifications.py
naas/runner/proxy.py
naas/runner/runner.py
naas/runner/scheduler.py
naas/runner/assets/down.png
naas/runner/assets/up.png
naas/runner/controllers/__init__.py
naas/runner/controllers/env.py
naas/runner/controllers/jobs.py
naas/runner/controllers/logs.py
naas/runner/controllers/notebooks.py
naas/runner/controllers/scheduler.py
naas/runner/controllers/static.py
naas/runner/html/error.html
naas/runner/html/manager.html
naas-0.0.17.data/scripts/naas
naas-0.0.17.dist-info/LICENSE
naas-0.0.17.dist-info/METADATA
naas-0.0.17.dist-info/WHEEL
naas-0.0.17.dist-info/top_level.txt
naas-0.0.17.dist-info/RECORD
